kuhl_haus/bedrock/api/__init__.py
kuhl_haus/bedrock/api/app.py
kuhl_haus/bedrock/api/env.py
kuhl_haus/bedrock/api/routers/__init__.py
kuhl_haus/bedrock/api/routers/chat.py
kuhl_haus/bedrock/api/routers/embeddings.py
kuhl_haus/bedrock/api/routers/model.py
kuhl_haus_bedrock_api-0.2.13.dist-info/METADATA
kuhl_haus_bedrock_api-0.2.13.dist-info/WHEEL
kuhl_haus_bedrock_api-0.2.13.dist-info/entry_points.txt
kuhl_haus_bedrock_api-0.2.13.dist-info/licenses/LICENSE.txt
kuhl_haus_bedrock_api-0.2.13.dist-info/RECORD
