Metadata-Version: 2.1
Name: kuhl-haus-bedrock-api
Version: 0.2.13
Summary: OpenAI-compatible REST API using AWS Bedrock as a backend
Author-Email: Tom Pounders <git@oldschool.engineer>
License: MIT
Classifier: Development Status :: 4 - Beta
Classifier: Programming Language :: Python
Project-URL: Homepage, https://github.com/kuhl-haus
Project-URL: Documentation, https://github.com/kuhl-haus/kuhl-haus-bedrock-api/wiki
Project-URL: Source, https://github.com/kuhl-haus/kuhl-haus-bedrock-api.git
Project-URL: Changelog, https://github.com/kuhl-haus/kuhl-haus-bedrock-api/commits
Project-URL: Tracker, https://github.com/kuhl-haus/kuhl-haus-bedrock-api/issues
Requires-Python: >=3.12
Requires-Dist: kuhl-haus-bedrock-app
Requires-Dist: kuhl-haus-metrics
Requires-Dist: uvicorn
Requires-Dist: fastapi
Requires-Dist: mangum
Requires-Dist: boto3
Requires-Dist: botocore
Requires-Dist: pydantic
Requires-Dist: numpy
Requires-Dist: requests
Requires-Dist: tiktoken
Requires-Dist: importlib-metadata
Requires-Dist: wheel
Provides-Extra: testing
Requires-Dist: setuptools; extra == "testing"
Requires-Dist: pdm-backend; extra == "testing"
Requires-Dist: pytest; extra == "testing"
Requires-Dist: pytest-cov; extra == "testing"
Requires-Dist: pytest-asyncio; extra == "testing"
Requires-Dist: httpx; extra == "testing"
Requires-Dist: starlette; extra == "testing"
